nonebot_plugin_report/__init__.py
nonebot_plugin_report/config.py
nonebot_plugin_report-1.3.1.dist-info/LICENSE
nonebot_plugin_report-1.3.1.dist-info/METADATA
nonebot_plugin_report-1.3.1.dist-info/WHEEL
nonebot_plugin_report-1.3.1.dist-info/RECORD
