Metadata-Version: 2.1
Name: nonebot-plugin-report
Version: 1.3.1
Summary: Push message from anywhere to your bot through webhook.
Home-page: https://github.com/syrinka/nonebot-plugin-report
License: AGPL-3.0
Keywords: nonebot,nonebot2
Author: syrinka
Author-email: syrinka@foxmail.com
Requires-Python: >=3.8.0,<4.0.0
Classifier: Development Status :: 5 - Production/Stable
Classifier: Environment :: Plugins
Classifier: License :: OSI Approved :: GNU Affero General Public License v3
Classifier: Programming Language :: Python :: 3
Classifier: Programming Language :: Python :: 3.8
Classifier: Programming Language :: Python :: 3.9
Classifier: Programming Language :: Python :: 3.10
Classifier: Programming Language :: Python :: 3.11
Classifier: Programming Language :: Python :: 3.12
Requires-Dist: nonebot2 (>=2.0.0,<3.0.0)
Project-URL: Repository, https://github.com/syrinka/nonebot-plugin-report
